{
  "JP": {
    "countryCode": "JP",
    "cityName": "東京",
    "tempC": 14.4,
    "humidity": 79,
    "weatherCode": 1,
    "asOf": "2026-05-11T06:45"
  },
  "US": {
    "countryCode": "US",
    "cityName": "ワシントンD.C.",
    "tempC": 25.1,
    "humidity": 42,
    "weatherCode": 2,
    "asOf": "2026-05-10T17:45"
  },
  "GB": {
    "countryCode": "GB",
    "cityName": "ロンドン",
    "tempC": 9.3,
    "humidity": 52,
    "weatherCode": 0,
    "asOf": "2026-05-10T22:45"
  },
  "DE": {
    "countryCode": "DE",
    "cityName": "ベルリン",
    "tempC": 14.7,
    "humidity": 56,
    "weatherCode": 3,
    "asOf": "2026-05-10T23:45"
  },
  "FR": {
    "countryCode": "FR",
    "cityName": "パリ",
    "tempC": 13.1,
    "humidity": 86,
    "weatherCode": 80,
    "asOf": "2026-05-10T23:45"
  },
  "CN": {
    "countryCode": "CN",
    "cityName": "北京",
    "tempC": 18.7,
    "humidity": 55,
    "weatherCode": 0,
    "asOf": "2026-05-11T05:45"
  },
  "KR": {
    "countryCode": "KR",
    "cityName": "ソウル",
    "tempC": 10.6,
    "humidity": 89,
    "weatherCode": 1,
    "asOf": "2026-05-11T06:45"
  },
  "IN": {
    "countryCode": "IN",
    "cityName": "ニューデリー",
    "tempC": 27.4,
    "humidity": 53,
    "weatherCode": 3,
    "asOf": "2026-05-11T03:15"
  },
  "BR": {
    "countryCode": "BR",
    "cityName": "ブラジリア",
    "tempC": 24.8,
    "humidity": 52,
    "weatherCode": 2,
    "asOf": "2026-05-10T18:45"
  },
  "AU": {
    "countryCode": "AU",
    "cityName": "キャンベラ",
    "tempC": 8.2,
    "humidity": 90,
    "weatherCode": 3,
    "asOf": "2026-05-11T07:45"
  }
}
