[
  {
    "id": "Al Jazeera-0-homes?traffic_source=rss",
    "headline": "‘Nothing left’: Hong Kong fire survivors return to burnt homes",
    "sourceName": "Al Jazeera",
    "sourceUrl": "https://www.aljazeera.com/video/newsfeed/2026/4/20/nothing-left-hong-kong-fire-survivors-return-to-burnt-homes?traffic_source=rss",
    "publishedAt": "2026-04-20T17:35:33.000Z",
    "countryCode": "QA",
    "lang": "en"
  },
  {
    "id": "Al Jazeera-1-an-do?traffic_source=rss",
    "headline": "These are difficult times for the world, so what will Pakistan do?",
    "sourceName": "Al Jazeera",
    "sourceUrl": "https://www.aljazeera.com/opinions/2026/4/20/these-are-difficult-times-for-the-world-so-what-will-pakistan-do?traffic_source=rss",
    "publishedAt": "2026-04-20T17:33:07.000Z",
    "countryCode": "QA",
    "lang": "en"
  },
  {
    "id": "El País-18-t-a-eduardo-mendoza.html",
    "headline": "Las juventudes de Junts agitan la semana de Sant Jordi llamando al boicot a Eduardo Mendoza",
    "sourceName": "El País",
    "sourceUrl": "https://elpais.com/espana/catalunya/2026-04-20/las-juventudes-de-junts-agitan-la-semana-de-sant-jordi-llamando-al-boicot-a-eduardo-mendoza.html",
    "publishedAt": "2026-04-20T17:33:02.000Z",
    "countryCode": "ES",
    "lang": "es"
  },
  {
    "id": "g1 Globo-0--ex-padrasto-natal.ghtml",
    "headline": "Menina de 7 anos é encontrada morta no quintal da casa de ex-padrasto em Natal",
    "sourceName": "g1 Globo",
    "sourceUrl": "https://g1.globo.com/rn/rio-grande-do-norte/noticia/2026/04/20/menina-morta-casa-ex-padrasto-natal.ghtml",
    "publishedAt": "2026-04-20T17:33:01.000Z",
    "countryCode": "BR",
    "lang": "pt"
  },
  {
    "id": "g1 Globo-1-versitario-nos-eua.ghtml",
    "headline": "Paraquedista bate em telão de estádio antes de jogo universitário nos EUA",
    "sourceName": "g1 Globo",
    "sourceUrl": "https://g1.globo.com/mundo/noticia/2026/04/20/paraquedista-bate-em-telao-de-estadio-antes-de-jogo-universitario-nos-eua.ghtml",
    "publishedAt": "2026-04-20T17:32:59.000Z",
    "countryCode": "BR",
    "lang": "pt"
  },
  {
    "id": "g1 Globo-2-cadas-em-lorena-sp.ghtml",
    "headline": "Justiça decreta prisão preventiva de homem acusado de matar ex-companheira a facadas, em Lorena (SP)",
    "sourceName": "g1 Globo",
    "sourceUrl": "https://g1.globo.com/sp/vale-do-paraiba-regiao/noticia/2026/04/20/justica-decreta-prisao-preventiva-de-homem-acusado-de-matar-ex-companheira-a-facadas-em-lorena-sp.ghtml",
    "publishedAt": "2026-04-20T17:32:52.000Z",
    "countryCode": "BR",
    "lang": "pt"
  },
  {
    "id": "g1 Globo-3-ado-loterias-caixa.ghtml",
    "headline": "Resultado das Loterias Caixa",
    "sourceName": "g1 Globo",
    "sourceUrl": "https://g1.globo.com/loterias/sorteios-caixa/ao-vivo/resultado-loterias-caixa.ghtml",
    "publishedAt": "2026-04-20T17:32:20.000Z",
    "countryCode": "BR",
    "lang": "pt"
  },
  {
    "id": "g1 Globo-4-ro-de-escola-no-ma.ghtml",
    "headline": "Polícia investiga ato análogo a estupro coletivo praticado por adolescentes contra estudante dentro de escola no MA",
    "sourceName": "g1 Globo",
    "sourceUrl": "https://g1.globo.com/ma/maranhao/noticia/2026/04/20/policia-investiga-ato-analogo-a-estupro-coletivo-praticado-por-adolescentes-contra-estudante-dentro-de-escola-no-ma.ghtml",
    "publishedAt": "2026-04-20T17:31:36.000Z",
    "countryCode": "BR",
    "lang": "pt"
  },
  {
    "id": "g1 Globo-5-da-dentro-da-nevoa.ghtml",
    "headline": "A 325 metros da Amazônia, cientistas encontram vida dentro da névoa",
    "sourceName": "g1 Globo",
    "sourceUrl": "https://g1.globo.com/sp/campinas-regiao/terra-da-gente/noticia/2026/04/20/a-325-metros-da-amazonia-cientistas-encontram-vida-dentro-da-nevoa.ghtml",
    "publishedAt": "2026-04-20T17:31:25.000Z",
    "countryCode": "BR",
    "lang": "pt"
  },
  {
    "id": "ANSA-3-6-a6d7-ecaf930a6663.html",
    "headline": "Brigitte Nielsen a Belve: \"Stallone mi ha distrutto la carriera\"",
    "sourceName": "ANSA",
    "sourceUrl": "https://www.ansa.it/sito/videogallery/spettacolo/2026/04/20/brigitte-nielsen-a-belve-stallone-mi-ha-distrutto-la-carriera_06dc8b0e-8157-4696-a6d7-ecaf930a6663.html",
    "publishedAt": "2026-04-20T17:29:35.000Z",
    "countryCode": "IT",
    "lang": "it"
  },
  {
    "id": "NHK-2-421/k10015104141000.html",
    "headline": "「北海道・三陸沖後発地震注意情報」 日頃からの備え確認を",
    "sourceName": "NHK",
    "sourceUrl": "http://www3.nhk.or.jp/news/html/20260421/k10015104141000.html",
    "publishedAt": "2026-04-20T17:28:10.000Z",
    "countryCode": "JP",
    "lang": "ja"
  },
  {
    "id": "DW-0-a=en-rss-en-all-1573-rdf",
    "headline": "Elon Musk skips probe as France investigates X",
    "sourceName": "DW",
    "sourceUrl": "https://www.dw.com/en/elon-musk-skips-probe-as-france-investigates-x/a-76864163?maca=en-rss-en-all-1573-rdf",
    "publishedAt": "2026-04-20T17:28:00.000Z",
    "countryCode": "DE",
    "lang": "en"
  },
  {
    "id": "The Guardian-25-ian-ship-ceasefire-doubt",
    "headline": "Middle East crisis live: Iran sends mixed signals on talks after US seizes ship",
    "sourceName": "The Guardian",
    "sourceUrl": "https://www.theguardian.com/world/live/2026/apr/20/iran-war-latest-news-updates-live-hormuz-trump-us-iranian-ship-ceasefire-doubt",
    "publishedAt": "2026-04-20T17:27:45.000Z",
    "countryCode": "GB",
    "lang": "en"
  },
  {
    "id": "The Hindu-0-icts/article70885514.ece",
    "headline": "Census 2027: training sessions kick off in districts",
    "sourceName": "The Hindu",
    "sourceUrl": "https://www.thehindu.com/news/national/kerala/census-2027-training-sessions-kick-off-in-districts/article70885514.ece",
    "publishedAt": "2026-04-20T17:27:07.000Z",
    "countryCode": "IN",
    "lang": "en"
  },
  {
    "id": "g1 Globo-6-0-de-abril-de-2026.ghtml",
    "headline": "VÍDEOS: JL1 de segunda-feira, 20 de abril de 2026",
    "sourceName": "g1 Globo",
    "sourceUrl": "https://g1.globo.com/pa/para/edicao/2026/04/20/videos-jl1-de-segunda-feira-20-de-abril-de-2026.ghtml",
    "publishedAt": "2026-04-20T17:26:05.000Z",
    "countryCode": "BR",
    "lang": "pt"
  },
  {
    "id": "g1 Globo-7-hecimento-estadual.ghtml",
    "headline": "Iniciativas inovadoras na gestão pública recebem reconhecimento estadual",
    "sourceName": "g1 Globo",
    "sourceUrl": "https://g1.globo.com/ce/ceara/especial-publicitario/sebrae-ceara/inovacao-e-negocios/noticia/2026/04/20/iniciativas-inovadoras-na-gestao-publica-recebem-reconhecimento-estadual.ghtml",
    "publishedAt": "2026-04-20T17:25:03.000Z",
    "countryCode": "BR",
    "lang": "pt"
  },
  {
    "id": "El País-23-ulto-en-su-maletero.html",
    "headline": "El músico D4VD, acusado formalmente por la Fiscalía del asesinato de una adolescente a la que ocultó en su maletero",
    "sourceName": "El País",
    "sourceUrl": "https://elpais.com/us/entretenimiento/2026-04-20/el-musico-d4vd-acusado-formalmente-por-la-fiscalia-del-asesinato-de-una-adolescente-a-la-que-oculto-en-su-maletero.html",
    "publishedAt": "2026-04-20T17:24:44.000Z",
    "countryCode": "ES",
    "lang": "es"
  },
  {
    "id": "ANSA-12-2-962f-d2a4fa1b1cbe.html",
    "headline": "Confindustria avverte: shock energia fino a 21 miliardi, scenario già peggiorato",
    "sourceName": "ANSA",
    "sourceUrl": "https://www.ansa.it/sito/notizie/economia/2026/04/20/confindustria-rischio-bolletta-energia-per-le-imprese-da-7-e-fino-a-21-miliardi_26dd3942-9371-4652-962f-d2a4fa1b1cbe.html",
    "publishedAt": "2026-04-20T17:24:37.000Z",
    "countryCode": "IT",
    "lang": "it"
  },
  {
    "id": "El País-1-tra-iran-en-directo.html",
    "headline": "Última hora de la guerra de Estados Unidos e Israel contra Irán, en directo | Pezeshkian acusa a EE UU de emitir “señales contradictorias”: “Los iraníes no se someten a la fuerza”",
    "sourceName": "El País",
    "sourceUrl": "https://elpais.com/internacional/2026-04-20/ultima-hora-de-la-guerra-de-estados-unidos-e-israel-contra-iran-en-directo.html",
    "publishedAt": "2026-04-20T17:24:24.000Z",
    "countryCode": "ES",
    "lang": "es"
  },
  {
    "id": "ANSA-11-f-928e-a080a910656d.html",
    "headline": "Trovano in casa una pistola e parte un colpo, muore un 17enne",
    "sourceName": "ANSA",
    "sourceUrl": "https://www.ansa.it/sito/notizie/cronaca/2026/04/20/maneggiano-pistola-trovata-in-casa-e-parte-un-colpo-muore-17enne_84328874-ad0a-4d0f-928e-a080a910656d.html",
    "publishedAt": "2026-04-20T17:24:09.000Z",
    "countryCode": "IT",
    "lang": "it"
  },
  {
    "id": "The Hindu-1-meet/article70885242.ece",
    "headline": "AIIMS Mangalagiri faculty delivers keynote address at Munich Global meet",
    "sourceName": "The Hindu",
    "sourceUrl": "https://www.thehindu.com/news/national/andhra-pradesh/aiims-mangalagiri-faculty-delivers-keynote-address-at-munich-global-meet/article70885242.ece",
    "publishedAt": "2026-04-20T17:21:57.000Z",
    "countryCode": "IN",
    "lang": "en"
  },
  {
    "id": "ANSA-6-3-aed7-f55d48f95589.html",
    "headline": "Medio Oriente, Trump: 'Non mi faccio mettere fretta, l'ultimatum scade mercoledì' - Liveblog",
    "sourceName": "ANSA",
    "sourceUrl": "https://www.ansa.it/sito/notizie/mondo/2026/04/20/medio-oriente-cnn-vance-vola-in-pakistan-martedi-negoziati-mercoledi.-teheran_67cea65a-390d-4e33-aed7-f55d48f95589.html",
    "publishedAt": "2026-04-20T17:20:54.000Z",
    "countryCode": "IT",
    "lang": "it"
  },
  {
    "id": "The Hindu-2-ning/article70884049.ece",
    "headline": "Poll bugle to fall silent across Tamil Nadu on Tuesday evening",
    "sourceName": "The Hindu",
    "sourceUrl": "https://www.thehindu.com/elections/tamil-nadu-assembly/poll-bugle-to-fall-silent-across-tamil-nadu-on-tuesday-evening/article70884049.ece",
    "publishedAt": "2026-04-20T17:20:41.000Z",
    "countryCode": "IN",
    "lang": "en"
  },
  {
    "id": "g1 Globo-8-rabalhando-no-tjms.ghtml",
    "headline": "Do afastamento à tornozeleira: quem é único desembargador suspeito de venda de sentenças que segue trabalhando no TJMS",
    "sourceName": "g1 Globo",
    "sourceUrl": "https://g1.globo.com/ms/mato-grosso-do-sul/noticia/2026/04/20/do-afastamento-a-tornozeleira-quem-e-unico-desembargador-suspeito-de-venda-de-sentencas-que-segue-trabalhando-no-tjms.ghtml",
    "publishedAt": "2026-04-20T17:20:20.000Z",
    "countryCode": "BR",
    "lang": "pt"
  },
  {
    "id": "g1 Globo-9-entivo-a-industria.ghtml",
    "headline": "Alckmin visita maior produtora de cloro da América do Sul e destaca medidas de incentivo à indústria",
    "sourceName": "g1 Globo",
    "sourceUrl": "https://g1.globo.com/sp/santos-regiao/noticia/2026/04/20/alckmin-visita-maior-produtora-de-cloro-da-america-do-sul-e-destaca-medidas-de-incentivo-a-industria.ghtml",
    "publishedAt": "2026-04-20T17:20:09.000Z",
    "countryCode": "BR",
    "lang": "pt"
  },
  {
    "id": "g1 Globo-10-a-cidade-no-parana.ghtml",
    "headline": "VÍDEO: homem agride companheira com ajuda de amigo e a abandona ferida em outra cidade, no Paraná",
    "sourceName": "g1 Globo",
    "sourceUrl": "https://g1.globo.com/pr/norte-noroeste/noticia/2026/04/20/homem-agride-companheira-abandona-ferida-em-outra-cidade-no-parana.ghtml",
    "publishedAt": "2026-04-20T17:20:06.000Z",
    "countryCode": "BR",
    "lang": "pt"
  },
  {
    "id": "g1 Globo-11-garota-14-anos-eua.ghtml",
    "headline": "Cantor D4vd é acusado de assassinato por morte de garota de 14 anos nos EUA",
    "sourceName": "g1 Globo",
    "sourceUrl": "https://g1.globo.com/pop-arte/noticia/2026/04/20/cantor-d4vd-acusado-morte-garota-14-anos-eua.ghtml",
    "publishedAt": "2026-04-20T17:19:30.000Z",
    "countryCode": "BR",
    "lang": "pt"
  },
  {
    "id": "g1 Globo-12-no-comercio-global.ghtml",
    "headline": "'O dilema de Malaca': por que outra passagem crítica para a navegação gera preocupação no comércio global",
    "sourceName": "g1 Globo",
    "sourceUrl": "https://g1.globo.com/mundo/noticia/2026/04/20/o-dilema-de-malaca-por-que-outra-passagem-critica-para-a-navegacao-gera-preocupacao-no-comercio-global.ghtml",
    "publishedAt": "2026-04-20T17:19:30.000Z",
    "countryCode": "BR",
    "lang": "pt"
  },
  {
    "id": "The Hindu-3-osts/article70885789.ece",
    "headline": "Allahabad HC judge recuses from Rahul Gandhi citizenship case, censures petitioner over social media posts",
    "sourceName": "The Hindu",
    "sourceUrl": "https://www.thehindu.com/news/national/hc-judge-recuses-from-rahul-gandhi-citizenship-case-censures-petitioner-over-social-media-posts/article70885789.ece",
    "publishedAt": "2026-04-20T17:19:20.000Z",
    "countryCode": "IN",
    "lang": "en"
  },
  {
    "id": "g1 Globo-13-nte-em-barra-mansa.ghtml",
    "headline": "Correção: acidente em Barra Mansa",
    "sourceName": "g1 Globo",
    "sourceUrl": "https://g1.globo.com/rj/sul-do-rio-costa-verde/noticia/2026/04/20/correcao-acidente-em-barra-mansa.ghtml",
    "publishedAt": "2026-04-20T17:19:19.000Z",
    "countryCode": "BR",
    "lang": "pt"
  },
  {
    "id": "g1 Globo-14-ual-no-norte-do-rs.ghtml",
    "headline": "Adolescente de 16 anos vinda de Manaus é resgatada de exploração sexual no Norte do RS",
    "sourceName": "g1 Globo",
    "sourceUrl": "https://g1.globo.com/rs/rio-grande-do-sul/noticia/2026/04/20/adolescente-de-16-anos-vinda-de-manaus-e-resgatada-de-exploracao-sexual-no-norte-do-rs.ghtml",
    "publishedAt": "2026-04-20T17:19:01.000Z",
    "countryCode": "BR",
    "lang": "pt"
  },
  {
    "id": "The Hindu-4-giri/article70885766.ece",
    "headline": "182 motorists booked during special drive against modified silencers in Malkajgiri",
    "sourceName": "The Hindu",
    "sourceUrl": "https://www.thehindu.com/news/national/telangana/182-motorists-booked-during-special-drive-against-modified-silencers-in-malkajgiri/article70885766.ece",
    "publishedAt": "2026-04-20T17:17:40.000Z",
    "countryCode": "IN",
    "lang": "en"
  },
  {
    "id": "Al Jazeera-2-ne-up?traffic_source=rss",
    "headline": "US launches tariff refund system as thousands of importers line up",
    "sourceName": "Al Jazeera",
    "sourceUrl": "https://www.aljazeera.com/economy/2026/4/20/us-launches-tariff-refund-system-as-thousands-of-importers-line-up?traffic_source=rss",
    "publishedAt": "2026-04-20T17:16:52.000Z",
    "countryCode": "QA",
    "lang": "en"
  },
  {
    "id": "El País-14-icos-de-alto-perfil.html",
    "headline": "Estados Unidos da un ultimátum de dos semanas a Cuba para que libere a presos políticos de alto perfil",
    "sourceName": "El País",
    "sourceUrl": "https://elpais.com/america/2026-04-20/estados-unidos-da-un-ultimatum-de-dos-semanas-a-cuba-para-que-libere-a-presos-politicos-de-alto-perfil.html",
    "publishedAt": "2026-04-20T17:16:15.000Z",
    "countryCode": "ES",
    "lang": "es"
  },
  {
    "id": "El País-24-ionarios-de-rosalia.html",
    "headline": "“Eres muy guapa pero te voy a arreglar un poco”: las 14 perlas de los confesionarios de Rosalía",
    "sourceName": "El País",
    "sourceUrl": "https://elpais.com/gente/2026-04-20/eres-muy-guapa-pero-te-voy-a-arreglar-un-poco-las-14-perlas-de-los-confesionarios-de-rosalia.html",
    "publishedAt": "2026-04-20T17:16:00.000Z",
    "countryCode": "ES",
    "lang": "es"
  },
  {
    "id": "g1 Globo-15-iminosa-por-engano.ghtml",
    "headline": "Integrante do Boi de Maracanã é encontrado morto após parar em área de facção criminosa por engano",
    "sourceName": "g1 Globo",
    "sourceUrl": "https://g1.globo.com/ma/maranhao/noticia/2026/04/20/integrante-do-boi-de-maracana-e-encontrado-morto-apos-parar-em-area-de-faccao-criminosa-por-engano.ghtml",
    "publishedAt": "2026-04-20T17:15:54.000Z",
    "countryCode": "BR",
    "lang": "pt"
  },
  {
    "id": "Al Jazeera-3--says?traffic_source=rss",
    "headline": "Lebanon, Israel to meet again Thursday for direct talks, US says",
    "sourceName": "Al Jazeera",
    "sourceUrl": "https://www.aljazeera.com/news/2026/4/20/lebanon-israel-to-meet-again-thursday-for-direct-talks-us-says?traffic_source=rss",
    "publishedAt": "2026-04-20T17:15:21.000Z",
    "countryCode": "QA",
    "lang": "en"
  },
  {
    "id": "The Hindu-5-n-ap/article70884852.ece",
    "headline": "Urea use stable despite 36% rise in cropped area in A.P.",
    "sourceName": "The Hindu",
    "sourceUrl": "https://www.thehindu.com/news/national/andhra-pradesh/urea-use-stable-despite-36-rise-in-cropped-area-in-ap/article70884852.ece",
    "publishedAt": "2026-04-20T17:14:49.000Z",
    "countryCode": "IN",
    "lang": "en"
  },
  {
    "id": "The Guardian-20--child-abuse-images-on-x",
    "headline": "Elon Musk snubs Paris legal summons over alleged child abuse images on X",
    "sourceName": "The Guardian",
    "sourceUrl": "https://www.theguardian.com/technology/2026/apr/20/french-prosecutors-summon-elon-musk-over-alleged-child-abuse-images-on-x",
    "publishedAt": "2026-04-20T17:14:00.000Z",
    "countryCode": "GB",
    "lang": "en"
  },
  {
    "id": "g1 Globo-16-a-entre-as-vitimas.ghtml",
    "headline": "Onda de assaltos assusta moradores no Complexo do Alemão; fundador do Voz das Comunidades está entre as vítimas",
    "sourceName": "g1 Globo",
    "sourceUrl": "https://g1.globo.com/rj/rio-de-janeiro/rj1/noticia/2026/04/20/onda-de-assaltos-assusta-moradores-no-complexo-do-alemao-fundador-do-voz-das-comunidades-esta-entre-as-vitimas.ghtml",
    "publishedAt": "2026-04-20T17:13:09.000Z",
    "countryCode": "BR",
    "lang": "pt"
  },
  {
    "id": "ANSA-17-d-86a2-c103c608db33.html",
    "headline": "Ucciso in un parcheggio a Pavia, fermato un ragazzo non ancora 17enne",
    "sourceName": "ANSA",
    "sourceUrl": "https://www.ansa.it/sito/notizie/cronaca/2026/04/20/omicidio-in-un-parcheggio-a-pavia-fermato-un-17enne_81ca751e-e1e9-41ed-86a2-c103c608db33.html",
    "publishedAt": "2026-04-20T17:13:02.000Z",
    "countryCode": "IT",
    "lang": "it"
  },
  {
    "id": "Al Jazeera-4--near?traffic_source=rss",
    "headline": "‘Everyone must calm down’, Macron urges as US-Iran talks near",
    "sourceName": "Al Jazeera",
    "sourceUrl": "https://www.aljazeera.com/video/newsfeed/2026/4/20/everyone-must-calm-down-macron-urges-as-us-iran-talks-near?traffic_source=rss",
    "publishedAt": "2026-04-20T17:11:45.000Z",
    "countryCode": "QA",
    "lang": "en"
  },
  {
    "id": "g1 Globo-17-ecida-em-rio-no-ac.ghtml",
    "headline": "Três dias após naufrágio de barco, bombeiros encontram rede de criança desaparecida em rio no AC",
    "sourceName": "g1 Globo",
    "sourceUrl": "https://g1.globo.com/ac/acre/noticia/2026/04/20/tres-dias-apos-naufragio-de-barco-bombeiros-encontram-rede-de-crianca-desaparecida-em-rio-no-ac.ghtml",
    "publishedAt": "2026-04-20T17:09:01.000Z",
    "countryCode": "BR",
    "lang": "pt"
  },
  {
    "id": "g1 Globo-18--dela-com-o-meu-pe.ghtml",
    "headline": "Voluntário faz relato dramático sobre buscas por brasileira durante prova de natação no Ironman Texas: 'Senti o corpo dela com o meu pé'",
    "sourceName": "g1 Globo",
    "sourceUrl": "https://g1.globo.com/sp/sao-paulo/noticia/2026/04/20/voluntario-faz-relato-dramatico-sobre-buscas-por-brasileira-durante-prova-de-natacao-no-ironman-texas-senti-o-corpo-dela-com-o-meu-pe.ghtml",
    "publishedAt": "2026-04-20T17:08:50.000Z",
    "countryCode": "BR",
    "lang": "pt"
  },
  {
    "id": "The Hindu-6-ours/article70884926.ece",
    "headline": "Tirupati police solve senior citizen murder case within 24 hours",
    "sourceName": "The Hindu",
    "sourceUrl": "https://www.thehindu.com/news/national/andhra-pradesh/tirupati-police-solve-senior-citizen-murder-case-within-24-hours/article70884926.ece",
    "publishedAt": "2026-04-20T17:08:17.000Z",
    "countryCode": "IN",
    "lang": "en"
  },
  {
    "id": "The Hindu-7--row/article70885304.ece",
    "headline": "Opening of ‘polling material room’ in Kozhikode kicks up a row",
    "sourceName": "The Hindu",
    "sourceUrl": "https://www.thehindu.com/news/national/kerala/opening-of-polling-material-room-in-kozhikode-kicks-up-a-row/article70885304.ece",
    "publishedAt": "2026-04-20T17:07:38.000Z",
    "countryCode": "IN",
    "lang": "en"
  },
  {
    "id": "g1 Globo-19-5-casos-em-3-meses.ghtml",
    "headline": "Furto de cobre de ar-condicionado preocupa empreendedores em Santana; 15 casos em 3 meses",
    "sourceName": "g1 Globo",
    "sourceUrl": "https://g1.globo.com/ap/amapa/noticia/2026/04/20/furto-de-cobre-de-ar-condicionado-preocupa-empreendedores-em-santana-15-casos-em-3-meses.ghtml",
    "publishedAt": "2026-04-20T17:07:32.000Z",
    "countryCode": "BR",
    "lang": "pt"
  },
  {
    "id": "g1 Globo-20-s-suspeito-e-preso.ghtml",
    "headline": "Cadela comunitária é morta a tiros em Pancas; suspeito é preso",
    "sourceName": "g1 Globo",
    "sourceUrl": "https://g1.globo.com/es/espirito-santo/norte-noroeste-es/noticia/2026/04/20/cadela-comunitaria-e-morta-a-tiros-em-pancas-suspeito-e-preso.ghtml",
    "publishedAt": "2026-04-20T17:07:32.000Z",
    "countryCode": "BR",
    "lang": "pt"
  },
  {
    "id": "g1 Globo-21-s-e-no-vale-do-aco.ghtml",
    "headline": "Feriado de Tiradentes: veja o que abre e fecha em Governador Valadares e no Vale do Aço",
    "sourceName": "g1 Globo",
    "sourceUrl": "https://g1.globo.com/mg/vales-mg/noticia/2026/04/20/feriado-de-tiradentes-veja-o-que-abre-e-fecha-em-governador-valadares-e-no-vale-do-aco.ghtml",
    "publishedAt": "2026-04-20T17:07:19.000Z",
    "countryCode": "BR",
    "lang": "pt"
  },
  {
    "id": "El País-0-os-ataques-cruzados.html",
    "headline": "Estados Unidos e Irán aproximan posturas para una nueva ronda de conversaciones, pese a los ataques cruzados",
    "sourceName": "El País",
    "sourceUrl": "https://elpais.com/internacional/2026-04-20/estados-unidos-e-iran-aproximan-posturas-para-una-nueva-ronda-de-conversaciones-pese-a-los-ataques-cruzados.html",
    "publishedAt": "2026-04-20T17:05:58.000Z",
    "countryCode": "ES",
    "lang": "es"
  },
  {
    "id": "ANSA-5-f-9d25-b2402d59dbac.html",
    "headline": "Alta attenzione del Colle sugli incentivi agli avvocati che seguono i rimpatri volontari. Mantovano vede Mattarella",
    "sourceName": "ANSA",
    "sourceUrl": "https://www.ansa.it/sito/notizie/politica/2026/04/20/alta-attenzione-del-colle-sugli-incentivi-agli-avvocati-che-seguono_2956ed8b-e64e-43bf-9d25-b2402d59dbac.html",
    "publishedAt": "2026-04-20T17:04:08.000Z",
    "countryCode": "IT",
    "lang": "it"
  },
  {
    "id": "The Hindu-8-ster/article70885808.ece",
    "headline": "Kondapalli festival to be held annually, says Minister",
    "sourceName": "The Hindu",
    "sourceUrl": "https://www.thehindu.com/news/national/andhra-pradesh/kondapalli-festival-to-be-held-annually-says-minister/article70885808.ece",
    "publishedAt": "2026-04-20T17:02:38.000Z",
    "countryCode": "IN",
    "lang": "en"
  },
  {
    "id": "g1 Globo-22-ivo/eua-ataque-ira.ghtml",
    "headline": "Negociação entre EUA e Irã segue incerta a 2 dias do fim da trégua; SIGA",
    "sourceName": "g1 Globo",
    "sourceUrl": "https://g1.globo.com/mundo/ao-vivo/eua-ataque-ira.ghtml",
    "publishedAt": "2026-04-20T17:02:00.000Z",
    "countryCode": "BR",
    "lang": "pt"
  },
  {
    "id": "g1 Globo-23-volucao-e-mudancas.ghtml",
    "headline": "Fuvest completa 50 anos e marca gerações com vestibular da USP; veja evolução e mudanças",
    "sourceName": "g1 Globo",
    "sourceUrl": "https://g1.globo.com/sp/sao-paulo/educacao/noticia/2026/04/20/fuvest-completa-50-anos-e-marca-geracoes-com-vestibular-da-usp-veja-evolucao-e-mudancas.ghtml",
    "publishedAt": "2026-04-20T17:01:43.000Z",
    "countryCode": "BR",
    "lang": "pt"
  },
  {
    "id": "The Hindu-9--cec/article70885572.ece",
    "headline": "Election Commission will leave no stone unturned for free, fair and transparent election in West Bengal: CEC",
    "sourceName": "The Hindu",
    "sourceUrl": "https://www.thehindu.com/elections/west-bengal-assembly/election-commission-will-leave-no-stone-unturned-for-free-fair-and-transparent-election-in-west-bengal-cec/article70885572.ece",
    "publishedAt": "2026-04-20T17:00:06.000Z",
    "countryCode": "IN",
    "lang": "en"
  },
  {
    "id": "The Hindu-10-ourt/article70885327.ece",
    "headline": "SOP issued for verification of assets declared by candidates during elections, Income-Tax departments tells Madras High Court",
    "sourceName": "The Hindu",
    "sourceUrl": "https://www.thehindu.com/news/national/tamil-nadu/sop-issued-for-verification-of-assets-declared-by-candidates-during-elections-income-tax-departments-tells-madras-high-court/article70885327.ece",
    "publishedAt": "2026-04-20T16:59:40.000Z",
    "countryCode": "IN",
    "lang": "en"
  },
  {
    "id": "The Hindu-11-lity/article70885784.ece",
    "headline": "Steps to address concerns of residents over structure plan in Kalamassery municipality",
    "sourceName": "The Hindu",
    "sourceUrl": "https://www.thehindu.com/news/national/kerala/steps-to-address-concerns-of-residents-over-structure-plan-in-kalamassery-municipality/article70885784.ece",
    "publishedAt": "2026-04-20T16:58:54.000Z",
    "countryCode": "IN",
    "lang": "en"
  },
  {
    "id": "g1 Globo-24-0-de-abril-de-2026.ghtml",
    "headline": "VÍDEOS: Bom Dia Acre desta segunda-feira, 20 de abril de 2026",
    "sourceName": "g1 Globo",
    "sourceUrl": "https://g1.globo.com/ac/acre/playlist/videos-bom-dia-acre-desta-segunda-feira-20-de-abril-de-2026.ghtml",
    "publishedAt": "2026-04-20T16:58:18.000Z",
    "countryCode": "BR",
    "lang": "pt"
  },
  {
    "id": "g1 Globo-25-ercent-em-campinas.ghtml",
    "headline": "De buracos a encanamento exposto: Pedidos por manutenção de calçadas crescem 26,8% em Campinas",
    "sourceName": "g1 Globo",
    "sourceUrl": "https://g1.globo.com/sp/campinas-regiao/noticia/2026/04/20/de-buracos-a-encanamento-exposto-pedidos-por-manutencao-de-calcadas-crescem-268percent-em-campinas.ghtml",
    "publishedAt": "2026-04-20T16:58:01.000Z",
    "countryCode": "BR",
    "lang": "pt"
  },
  {
    "id": "The Hindu-12--cji/article70885699.ece",
    "headline": "Digital arrest is a crime against human dignity: CJI",
    "sourceName": "The Hindu",
    "sourceUrl": "https://www.thehindu.com/news/national/digital-arrest-is-a-crime-against-human-dignity-cji/article70885699.ece",
    "publishedAt": "2026-04-20T16:55:39.000Z",
    "countryCode": "IN",
    "lang": "en"
  },
  {
    "id": "The Hindu-13-draa/article70885719.ece",
    "headline": "KCR alleges govt. okayed Centre’s proposal to install meters to farm pumpsets,  flays HYDRAA",
    "sourceName": "The Hindu",
    "sourceUrl": "https://www.thehindu.com/news/national/telangana/kcr-alleges-govt-okayed-centres-proposal-to-install-meters-to-farm-pumpsets-flays-hydraa/article70885719.ece",
    "publishedAt": "2026-04-20T16:55:30.000Z",
    "countryCode": "IN",
    "lang": "en"
  },
  {
    "id": "g1 Globo-26-incendio-na-mg-214.ghtml",
    "headline": "Micro-ônibus que transportava time de futebol é destruído por incêndio na MG-214",
    "sourceName": "g1 Globo",
    "sourceUrl": "https://g1.globo.com/mg/grande-minas/noticia/2026/04/20/micro-onibus-que-transportava-time-de-futebol-e-destruido-por-incendio-na-mg-214.ghtml",
    "publishedAt": "2026-04-20T16:52:02.000Z",
    "countryCode": "BR",
    "lang": "pt"
  },
  {
    "id": "g1 Globo-27-0-de-abril-de-2026.ghtml",
    "headline": "VÍDEOS: Jornal Anhanguera 1ª Edição-TO de segunda-feira, 20 de abril de 2026",
    "sourceName": "g1 Globo",
    "sourceUrl": "https://g1.globo.com/to/tocantins/playlist/videos-jornal-anhanguera-1-edicao-to-de-segunda-feira-20-de-abril-de-2026.ghtml",
    "publishedAt": "2026-04-20T16:49:59.000Z",
    "countryCode": "BR",
    "lang": "pt"
  },
  {
    "id": "Al Jazeera-5-gorge?traffic_source=rss",
    "headline": "At least 21 killed as bus crashes into Kashmir gorge",
    "sourceName": "Al Jazeera",
    "sourceUrl": "https://www.aljazeera.com/news/2026/4/20/at-least-21-killed-as-bus-skids-off-kashmir-road-into-gorge?traffic_source=rss",
    "publishedAt": "2026-04-20T16:48:44.000Z",
    "countryCode": "QA",
    "lang": "en"
  },
  {
    "id": "Al Jazeera-6-d-adf?traffic_source=rss",
    "headline": "Ugandan and Congolese forces rescue 200 from ISIL-backed ADF",
    "sourceName": "Al Jazeera",
    "sourceUrl": "https://www.aljazeera.com/news/2026/4/20/ugandan-and-congolese-forces-rescue-200-from-isil-backed-adf?traffic_source=rss",
    "publishedAt": "2026-04-20T16:48:16.000Z",
    "countryCode": "QA",
    "lang": "en"
  },
  {
    "id": "The Hindu-14-amme/article70885564.ece",
    "headline": "Students gain hands-on experience on drone technology at outreach programme",
    "sourceName": "The Hindu",
    "sourceUrl": "https://www.thehindu.com/news/national/andhra-pradesh/students-gain-hands-on-experience-on-drone-technology-at-outreach-programme/article70885564.ece",
    "publishedAt": "2026-04-20T16:46:40.000Z",
    "countryCode": "IN",
    "lang": "en"
  },
  {
    "id": "g1 Globo-28-0-de-abril-de-2026.ghtml",
    "headline": "VÍDEOS: EPTV 1 Sul de Minas de segunda-feira, 20 de abril de 2026",
    "sourceName": "g1 Globo",
    "sourceUrl": "https://g1.globo.com/mg/sul-de-minas/edicao/2026/04/20/videos-eptv-1-sul-de-minas-de-segunda-feira-20-de-abril-de-2026.ghtml",
    "publishedAt": "2026-04-20T16:46:34.000Z",
    "countryCode": "BR",
    "lang": "pt"
  },
  {
    "id": "g1 Globo-29-r-153-em-rio-preto.ghtml",
    "headline": "PRF apreende remédio para emagrecer escondido em frascos de xampu e cremes na BR-153 em Rio Preto",
    "sourceName": "g1 Globo",
    "sourceUrl": "https://g1.globo.com/sp/sao-jose-do-rio-preto-aracatuba/noticia/2026/04/20/prf-apreende-remedio-para-emagrecer-escondido-em-frascos-de-xampu-e-cremes-na-br-153-em-rio-preto.ghtml",
    "publishedAt": "2026-04-20T16:46:32.000Z",
    "countryCode": "BR",
    "lang": "pt"
  },
  {
    "id": "The Hindu-15-toll/article70883306.ece",
    "headline": "21 killed, over 61 injured after bus tumbles down hillside in Jammu’s Udhampur",
    "sourceName": "The Hindu",
    "sourceUrl": "https://www.thehindu.com/news/national/jammu-and-kashmir/bus-accident-in-jammu-and-kashmir-udhampur-death-toll/article70883306.ece",
    "publishedAt": "2026-04-20T16:45:43.000Z",
    "countryCode": "IN",
    "lang": "en"
  },
  {
    "id": "The Hindu-16-line/article70885709.ece",
    "headline": "IISc’s Centre for Brain Research launches ₹2 crore AI challenge for early detection of cognitive decline",
    "sourceName": "The Hindu",
    "sourceUrl": "https://www.thehindu.com/news/national/karnataka/iiscs-centre-for-brain-research-launches-2-crore-ai-challenge-for-early-detection-of-cognitive-decline/article70885709.ece",
    "publishedAt": "2026-04-20T16:44:35.000Z",
    "countryCode": "IN",
    "lang": "en"
  },
  {
    "id": "The Hindu-17-l-25/article70885512.ece",
    "headline": "Summer camp in Vijayawada from April 25",
    "sourceName": "The Hindu",
    "sourceUrl": "https://www.thehindu.com/news/national/andhra-pradesh/summer-camp-in-vijayawada-from-april-25/article70885512.ece",
    "publishedAt": "2026-04-20T16:43:17.000Z",
    "countryCode": "IN",
    "lang": "en"
  },
  {
    "id": "The Hindu-18-rife/article70847668.ece",
    "headline": "Tamil Nadu election 2026: Another son rises in Pennagaram constituency from PMK’s fratricidal strife",
    "sourceName": "The Hindu",
    "sourceUrl": "https://www.thehindu.com/elections/tamil-nadu-assembly/another-son-rises-in-pennagaram-from-pmks-fratricidal-strife/article70847668.ece",
    "publishedAt": "2026-04-20T16:43:03.000Z",
    "countryCode": "IN",
    "lang": "en"
  },
  {
    "id": "The Hindu-19-s-cm/article70885682.ece",
    "headline": "Cong. will return to power with over 100 seats after next elections, says CM",
    "sourceName": "The Hindu",
    "sourceUrl": "https://www.thehindu.com/news/national/telangana/cong-will-return-to-power-with-over-100-seats-after-next-elections-says-cm/article70885682.ece",
    "publishedAt": "2026-04-20T16:42:20.000Z",
    "countryCode": "IN",
    "lang": "en"
  },
  {
    "id": "France 24-0-lson-vetting-controversy",
    "headline": "REPLAY: UK PM Starmer faces parliament over Mandelson vetting controversy",
    "sourceName": "France 24",
    "sourceUrl": "https://www.france24.com/en/video/20260420-replay-uk-pm-starmer-faces-parliament-over-mandelson-vetting-controversy",
    "publishedAt": "2026-04-20T16:42:19.000Z",
    "countryCode": "FR",
    "lang": "en"
  },
  {
    "id": "The Hindu-20-ison/article70885630.ece",
    "headline": "Both are actors who took the political route, but MGR-Vijay is a facile comparison",
    "sourceName": "The Hindu",
    "sourceUrl": "https://www.thehindu.com/elections/tamil-nadu-assembly/both-are-actors-who-took-the-political-route-but-mgr-vijay-is-a-facile-comparison/article70885630.ece",
    "publishedAt": "2026-04-20T16:39:45.000Z",
    "countryCode": "IN",
    "lang": "en"
  },
  {
    "id": "The Hindu-21-rugs/article70884629.ece",
    "headline": "A Malayalam blockbuster film reignites debate over efficacy of Ayurvedic drugs",
    "sourceName": "The Hindu",
    "sourceUrl": "https://www.thehindu.com/news/national/kerala/a-malayalam-blockbuster-film-reignites-debate-over-efficacy-of-ayurvedic-drugs/article70884629.ece",
    "publishedAt": "2026-04-20T16:39:11.000Z",
    "countryCode": "IN",
    "lang": "en"
  },
  {
    "id": "The Hindu-22-oard/article70883388.ece",
    "headline": "Hyderabad to Hubbali flight diverted to Bengaluru after turbulence sparks panic onboard",
    "sourceName": "The Hindu",
    "sourceUrl": "https://www.thehindu.com/news/cities/Hyderabad/fly91-hyderabad-to-hubbali-flight-diverted-to-bengaluru-after-turbulence-sparks-panic-onboard/article70883388.ece",
    "publishedAt": "2026-04-20T16:38:18.000Z",
    "countryCode": "IN",
    "lang": "en"
  },
  {
    "id": "El País-15-tan-sus-solicitudes.html",
    "headline": "Largas colas y confusión en el primer día para la regularización: “No tengo certificado digital y es imposible que saque cita previa”",
    "sourceName": "El País",
    "sourceUrl": "https://elpais.com/espana/2026-04-20/comienza-el-plazo-para-la-regularizacion-de-forma-presencial-mas-de-400-oficinas-atienden-a-los-inmigrantes-que-presentan-sus-solicitudes.html",
    "publishedAt": "2026-04-20T16:36:57.000Z",
    "countryCode": "ES",
    "lang": "es"
  },
  {
    "id": "The Hindu-23-ated/article70885244.ece",
    "headline": "Sholinganallur AIADMK candidate says DMK failed to maintain assets that party created",
    "sourceName": "The Hindu",
    "sourceUrl": "https://www.thehindu.com/news/cities/chennai/sholinganallur-aiadmk-candidate-says-dmk-failed-to-maintain-assets-that-party-created/article70885244.ece",
    "publishedAt": "2026-04-20T16:35:08.000Z",
    "countryCode": "IN",
    "lang": "en"
  },
  {
    "id": "ANSA-15-5-8a7d-b14c720ea3a5.html",
    "headline": "Addio a Desmond Morris, l'etologo della 'scimmia nuda'",
    "sourceName": "ANSA",
    "sourceUrl": "https://www.ansa.it/canale_scienza/notizie/biotech/2026/04/20/addio-a-desmond-morris-letologo-della-scimmia-nuda-_201babd3-412c-4025-8a7d-b14c720ea3a5.html",
    "publishedAt": "2026-04-20T16:34:54.000Z",
    "countryCode": "IT",
    "lang": "it"
  },
  {
    "id": "NHK-0-421/k10015104151000.html",
    "headline": "H3ロケット JAXAが6月10日の打ち上げ再開に向け調整進める",
    "sourceName": "NHK",
    "sourceUrl": "http://www3.nhk.or.jp/news/html/20260421/k10015104151000.html",
    "publishedAt": "2026-04-20T16:33:10.000Z",
    "countryCode": "JP",
    "lang": "ja"
  },
  {
    "id": "The Hindu-24-ctor/article70885209.ece",
    "headline": "YSRCP leader flags failures in NTR district, submits 12-point petition to Collector",
    "sourceName": "The Hindu",
    "sourceUrl": "https://www.thehindu.com/news/national/andhra-pradesh/ysrcp-leader-flags-failures-in-ntr-district-submits-12-point-petition-to-collector/article70885209.ece",
    "publishedAt": "2026-04-20T16:32:48.000Z",
    "countryCode": "IN",
    "lang": "en"
  },
  {
    "id": "The Hindu-25-e-it/article70884114.ece",
    "headline": "Fire breaks out in Rajasthan HPCL refinery, PM Modi cancels planned inauguration",
    "sourceName": "The Hindu",
    "sourceUrl": "https://www.thehindu.com/news/national/fire-breaks-out-in-rajasthan-hpcl-refinery-a-day-before-pm-modi-was-to-inaugurate-it/article70884114.ece",
    "publishedAt": "2026-04-20T16:32:43.000Z",
    "countryCode": "IN",
    "lang": "en"
  },
  {
    "id": "ANSA-24-f-9aad-9bcecc382f8a.html",
    "headline": "Massacro in Louisiana, il killer padre di 7 dei bimbi uccisi",
    "sourceName": "ANSA",
    "sourceUrl": "https://www.ansa.it/sito/notizie/mondo/2026/04/20/sette-degli-otto-bimbi-uccisi-in-louisiana-erano-figli-del-killer._87d135ab-c67d-40bf-9aad-9bcecc382f8a.html",
    "publishedAt": "2026-04-20T16:30:52.000Z",
    "countryCode": "IT",
    "lang": "it"
  },
  {
    "id": "ANSA-18-5-9936-f36f59d095b1.html",
    "headline": "Giappone in allarme dopo una scossa da 7.7 e l'allerta tsunami",
    "sourceName": "ANSA",
    "sourceUrl": "https://www.ansa.it/sito/notizie/mondo/2026/04/20/giappone-in-allarme-dopo-una-scossa-da-7.7-e-lallerta-tsunami_375b686b-81a2-4ab5-9936-f36f59d095b1.html",
    "publishedAt": "2026-04-20T16:29:41.000Z",
    "countryCode": "IT",
    "lang": "it"
  },
  {
    "id": "The Hindu-26-icts/article70885794.ece",
    "headline": "Complete mapping of voters by April end: Telangana CEO to DEOs of urban districts",
    "sourceName": "The Hindu",
    "sourceUrl": "https://www.thehindu.com/news/cities/Hyderabad/complete-mapping-of-voters-by-april-end-telangana-ceo-to-deos-of-urban-districts/article70885794.ece",
    "publishedAt": "2026-04-20T16:28:36.000Z",
    "countryCode": "IN",
    "lang": "en"
  },
  {
    "id": "Al Jazeera-7--most?traffic_source=rss",
    "headline": "Iran expands limited internet access but restrictions remain for most",
    "sourceName": "Al Jazeera",
    "sourceUrl": "https://www.aljazeera.com/news/2026/4/20/iran-expands-limited-internet-access-but-restrictions-remain-for-most?traffic_source=rss",
    "publishedAt": "2026-04-20T16:28:08.000Z",
    "countryCode": "QA",
    "lang": "en"
  },
  {
    "id": "The Hindu-27-alli/article70885796.ece",
    "headline": "Three-year-old girl killed in stray dog attack in Peddapalli",
    "sourceName": "The Hindu",
    "sourceUrl": "https://www.thehindu.com/news/national/telangana/three-year-old-girl-killed-in-stray-dog-attack-in-peddapalli/article70885796.ece",
    "publishedAt": "2026-04-20T16:27:31.000Z",
    "countryCode": "IN",
    "lang": "en"
  },
  {
    "id": "The Hindu-28-gavi/article70885350.ece",
    "headline": "Officials send straying elephant safely back to forest in Belagavi",
    "sourceName": "The Hindu",
    "sourceUrl": "https://www.thehindu.com/news/national/karnataka/officials-send-straying-elephant-safely-back-to-forest-in-belagavi/article70885350.ece",
    "publishedAt": "2026-04-20T16:26:32.000Z",
    "countryCode": "IN",
    "lang": "en"
  },
  {
    "id": "BBC World-6-dium=RSS&at_campaign=rss",
    "headline": "More than 200 rescued from IS-linked group in DR Congo",
    "sourceName": "BBC World",
    "sourceUrl": "https://www.bbc.com/news/articles/cy7144jr68lo?at_medium=RSS&at_campaign=rss",
    "publishedAt": "2026-04-20T16:25:12.000Z",
    "countryCode": "GB",
    "lang": "en"
  },
  {
    "id": "The Hindu-29-ttai/article70847806.ece",
    "headline": "Tamil Nadu election 2026: Farmers in Nilakottai constituency want government perfume factory",
    "sourceName": "The Hindu",
    "sourceUrl": "https://www.thehindu.com/elections/tamil-nadu-assembly/farmers-want-government-perfume-factory-in-nilakottai/article70847806.ece",
    "publishedAt": "2026-04-20T16:24:51.000Z",
    "countryCode": "IN",
    "lang": "en"
  },
  {
    "id": "ANSA-7-a-bdf5-903995ed4192.html",
    "headline": "Arrivano le fatture per i feriti di Crans Montana, l'ambasciatore 'nulla è dovuto'",
    "sourceName": "ANSA",
    "sourceUrl": "https://www.ansa.it/sito/notizie/cronaca/2026/04/20/arrivano-le-fatture-per-i-feriti-di-crans-montana-lambasciatore-nulla-e-dovuto_f29283ad-b393-41ca-bdf5-903995ed4192.html",
    "publishedAt": "2026-04-20T16:24:38.000Z",
    "countryCode": "IT",
    "lang": "it"
  },
  {
    "id": "ANSA-19-6-9fa4-85fe508f7d3c.html",
    "headline": "Starmer ai Comuni: 'Non avrei dovuto nominare Mandelson'",
    "sourceName": "ANSA",
    "sourceUrl": "https://www.ansa.it/sito/notizie/mondo/2026/04/20/starmer-ai-comuni-non-avrei-dovuto-nominare-mandelson_4d478d01-f400-45a6-9fa4-85fe508f7d3c.html",
    "publishedAt": "2026-04-20T16:21:25.000Z",
    "countryCode": "IT",
    "lang": "it"
  },
  {
    "id": "El País-19-as-administraciones.html",
    "headline": "El Gobierno ultima el decreto que activará la jubilación parcial del personal laboral de las administraciones",
    "sourceName": "El País",
    "sourceUrl": "https://elpais.com/economia/2026-04-20/el-gobierno-ultima-el-decreto-que-activara-la-jubilacion-parcial-del-personal-laboral-de-las-administraciones.html",
    "publishedAt": "2026-04-20T16:20:53.000Z",
    "countryCode": "ES",
    "lang": "es"
  },
  {
    "id": "ANSA-13-9-babb-eebe6df55120.html",
    "headline": "In un video in timelapse il traffico marittimo nello Stretto di Hormuz e nel Golfo dell'Oman",
    "sourceName": "ANSA",
    "sourceUrl": "https://www.ansa.it/sito/videogallery/mondo/2026/04/20/in-un-video-in-timelapse-il-traffico-marittimo-nello-stretto-di-hormuz-e-nel-golfo-delloman_0b990b15-b569-4b09-babb-eebe6df55120.html",
    "publishedAt": "2026-04-20T16:18:12.000Z",
    "countryCode": "IT",
    "lang": "it"
  },
  {
    "id": "ANSA-10-3-b74b-97ea01021535.html",
    "headline": "Il Garante della Privacy sanziona Poste Italiane e Postepay per oltre 12,5 milioni",
    "sourceName": "ANSA",
    "sourceUrl": "https://www.ansa.it/sito/notizie/economia/2026/04/20/garante-privacy-sanziona-poste-italiane-e-postepay-per-oltre-125-milioni_ffea7f4f-afab-4053-b74b-97ea01021535.html",
    "publishedAt": "2026-04-20T16:16:33.000Z",
    "countryCode": "IT",
    "lang": "it"
  },
  {
    "id": "El País-6-a-machado-en-madrid.html",
    "headline": "Carlos Baute se disculpa por los insultos racistas a Delcy Rodríguez durante el acto de María Corina Machado en Madrid",
    "sourceName": "El País",
    "sourceUrl": "https://elpais.com/gente/2026-04-20/carlos-baute-se-disculpa-por-los-insultos-racistas-a-delcy-rodriguez-durante-el-acto-de-maria-corina-machado-en-madrid.html",
    "publishedAt": "2026-04-20T16:13:13.000Z",
    "countryCode": "ES",
    "lang": "es"
  },
  {
    "id": "Al Jazeera-8-sease?traffic_source=rss",
    "headline": "Former Afghanistan cricketer Shapoor Zadran battles life-threatening disease",
    "sourceName": "Al Jazeera",
    "sourceUrl": "https://www.aljazeera.com/sports/2026/4/20/former-afghanistan-cricketer-shapoor-zadran-battles-life-threatening-disease?traffic_source=rss",
    "publishedAt": "2026-04-20T16:11:06.000Z",
    "countryCode": "QA",
    "lang": "en"
  },
  {
    "id": "El País-25--pidio-cuatro-veces.html",
    "headline": "El lotero juzgado por robar el boleto de los 4,7 millones sostiene que no tenía “ánimo de cobrar” el premio, aunque lo pidió cuatro veces",
    "sourceName": "El País",
    "sourceUrl": "https://elpais.com/espana/galicia/2026-04-20/el-lotero-juzgado-por-robar-el-boleto-de-los-47-millones-sostiene-que-no-tenia-animo-de-cobrar-el-premio-aunque-lo-pidio-cuatro-veces.html",
    "publishedAt": "2026-04-20T16:10:54.000Z",
    "countryCode": "ES",
    "lang": "es"
  },
  {
    "id": "El País-13-e-tomaba-decisiones.html",
    "headline": "La comisión parlamentaria sobre la dana acaba  con la expulsión de un diputado del PP: “Haga el favor de callar”",
    "sourceName": "El País",
    "sourceUrl": "https://elpais.com/espana/2026-04-20/un-jefe-de-la-aemet-sobre-la-dana-a-las-cinco-estaba-claro-que-media-provincia-de-valencia-estaba-inundada-y-nadie-tomaba-decisiones.html",
    "publishedAt": "2026-04-20T16:04:23.000Z",
    "countryCode": "ES",
    "lang": "es"
  }
]
